qt_extras/__init__.py
qt_extras/autofit.py
qt_extras/info.py
qt_extras/list_button.py
qt_extras/list_layout.py
qt_extras/menu_button.py
qt_extras/shuffle_grid.py
soso_qt_extras-1.6.3.dist-info/entry_points.txt
soso_qt_extras-1.6.3.dist-info/LICENSE
soso_qt_extras-1.6.3.dist-info/WHEEL
soso_qt_extras-1.6.3.dist-info/METADATA
soso_qt_extras-1.6.3.dist-info/RECORD
