Metadata-Version: 2.1
Name: soso_qt_extras
Version: 1.6.3
Summary: Provides various extras for PyQt.
Author-email: Leon Dionne <ldionne@dridesign.sh.cn>
Classifier: License :: OSI Approved :: GNU General Public License v3 or later (GPLv3+)
Requires-Dist: PyQt5
Project-URL: Home, https://github.com/Zen-Master-SoSo/qt_extras
